<?xml version="1.0" encoding="UTF-8"?>
<!DOCTYPE plist PUBLIC "-//Apple Computer//DTD PLIST 1.0//EN" "http://www.apple.com/DTDs/PropertyList-1.0.dtd">
<plist version="1.0">
<dict>
	<key>Major Version</key><integer>1</integer>
	<key>Minor Version</key><integer>1</integer>
	<key>Date</key><date>2017-03-12T07:36:56Z</date>
	<key>Application Version</key><string>12.5.5.5</string>
	<key>Features</key><integer>5</integer>
	<key>Show Content Ratings</key><true/>
	<key>Music Folder</key><string>file:///Volumes/LAVALAMP/music/iTunes/</string>
	<key>Library Persistent ID</key><string>E988D0C119B8D19C</string>
	<key>Tracks</key>
	<dict>
		<key>12311</key>
		<dict>
			<key>Track ID</key><integer>12311</integer>
			<key>Name</key><string>Way Down Boogie</string>
			<key>Artist</key><string>Harold Burrage</string>
			<key>Album</key><string>Rhythm 'N' Blues - Boogie Woogie Goodies</string>
			<key>Kind</key><string>MPEG audio file</string>
			<key>Size</key><integer>7080002</integer>
			<key>Total Time</key><integer>172591</integer>
			<key>Year</key><integer>1952</integer>
			<key>Date Modified</key><date>2017-02-20T18:55:34Z</date>
			<key>Date Added</key><date>2017-02-18T07:48:40Z</date>
			<key>Bit Rate</key><integer>320</integer>
			<key>Sample Rate</key><integer>44100</integer>
			<key>Play Count</key><integer>3</integer>
			<key>Play Date</key><integer>3571751638</integer>
			<key>Play Date UTC</key><date>2017-03-08T01:13:58Z</date>
			<key>Skip Count</key><integer>1</integer>
			<key>Skip Date</key><date>2017-03-08T02:06:12Z</date>
			<key>Rating</key><integer>100</integer>
			<key>Album Rating</key><integer>100</integer>
			<key>Album Rating Computed</key><true/>
			<key>Artwork Count</key><integer>1</integer>
			<key>Sort Album</key><string>Rhythm 'N' Blues - Boogie Woogie Goodies</string>
			<key>Persistent ID</key><string>DF4C8A1A3ACD0FDC</string>
			<key>Track Type</key><string>File</string>
			<key>Location</key><string>file:///Volumes/LAVALAMP/music/iTunes/Rhythm%20'N'%20Blues%20-%20Boogie%20Woogie%20Goodies%20-%204CD-BOX/19.%20Way%20Down%20Boogie.mp3</string>
			<key>File Folder Count</key><integer>3</integer>
			<key>Library Folder Count</key><integer>1</integer>
		</dict>
		<key>12349</key>
		<dict>
			<key>Track ID</key><integer>12349</integer>
			<key>Name</key><string>Mischievious Boogie (1951)</string>
			<key>Artist</key><string>Big Mama Thornton</string>
			<key>Album</key><string>Rhythm 'N' Blues - Boogie Woogie Goodies</string>
			<key>Kind</key><string>MPEG audio file</string>
			<key>Size</key><integer>6270078</integer>
			<key>Total Time</key><integer>152346</integer>
			<key>Year</key><integer>1951</integer>
			<key>Date Modified</key><date>2017-02-20T19:03:41Z</date>
			<key>Date Added</key><date>2017-02-18T07:48:40Z</date>
			<key>Bit Rate</key><integer>320</integer>
			<key>Sample Rate</key><integer>44100</integer>
			<key>Play Count</key><integer>4</integer>
			<key>Play Date</key><integer>3571752314</integer>
			<key>Play Date UTC</key><date>2017-03-08T01:25:14Z</date>
			<key>Skip Count</key><integer>1</integer>
			<key>Skip Date</key><date>2017-02-20T19:03:50Z</date>
			<key>Rating</key><integer>100</integer>
			<key>Album Rating</key><integer>60</integer>
			<key>Artwork Count</key><integer>1</integer>
			<key>Sort Album</key><string>Rhythm 'N' Blues - Boogie Woogie Goodies</string>
			<key>Sort Artist</key><string>Big Mama Thornton</string>
			<key>Persistent ID</key><string>1D3DD8E47A8D9EE1</string>
			<key>Track Type</key><string>File</string>
			<key>Location</key><string>file:///Volumes/LAVALAMP/music/iTunes/Rhythm%20'N'%20Blues%20-%20Boogie%20Woogie%20Goodies%20-%204CD-BOX/55.%20Mischievious%20Boogie%20%20(1951).mp3</string>
			<key>File Folder Count</key><integer>3</integer>
			<key>Library Folder Count</key><integer>1</integer>
		</dict>
		<key>12367</key>
		<dict>
			<key>Track ID</key><integer>12367</integer>
			<key>Name</key><string>Kissin' Bug Boogie (1950)</string>
			<key>Artist</key><string>Crown Prince Waterford</string>
			<key>Album</key><string>Rhythm 'N' Blues - Boogie Woogie Goodies</string>
			<key>Kind</key><string>MPEG audio file</string>
			<key>Size</key><integer>6387107</integer>
			<key>Total Time</key><integer>155271</integer>
			<key>Year</key><integer>1950</integer>
			<key>Date Modified</key><date>2017-02-20T19:07:39Z</date>
			<key>Date Added</key><date>2017-02-18T07:48:40Z</date>
			<key>Bit Rate</key><integer>320</integer>
			<key>Sample Rate</key><integer>44100</integer>
			<key>Play Count</key><integer>2</integer>
			<key>Play Date</key><integer>3571752827</integer>
			<key>Play Date UTC</key><date>2017-03-08T01:33:47Z</date>
			<key>Skip Count</key><integer>1</integer>
			<key>Skip Date</key><date>2017-02-20T19:07:41Z</date>
			<key>Rating</key><integer>100</integer>
			<key>Album Rating</key><integer>60</integer>
			<key>Artwork Count</key><integer>1</integer>
			<key>Sort Album</key><string>Rhythm 'N' Blues - Boogie Woogie Goodies</string>
			<key>Sort Artist</key><string>Crown Prince Waterford</string>
			<key>Persistent ID</key><string>F526F762BA278B89</string>
			<key>Track Type</key><string>File</string>
			<key>Location</key><string>file:///Volumes/LAVALAMP/music/iTunes/Rhythm%20'N'%20Blues%20-%20Boogie%20Woogie%20Goodies%20-%204CD-BOX/74.%20Kissin'%20Bug%20Boogie%20%20(1950).mp3</string>
			<key>File Folder Count</key><integer>3</integer>
			<key>Library Folder Count</key><integer>1</integer>
		</dict>
		<key>12803</key>
		<dict>
			<key>Track ID</key><integer>12803</integer>
			<key>Name</key><string>Copper colored gal</string>
			<key>Artist</key><string>Fats Waller</string>
			<key>Album</key><string>The Complete Recorded Works Vol 4.1 1936-1937</string>
			<key>Kind</key><string>MPEG audio file</string>
			<key>Size</key><integer>7226039</integer>
			<key>Total Time</key><integer>175333</integer>
			<key>Track Number</key><integer>2</integer>
			<key>Date Modified</key><date>2017-02-20T20:09:30Z</date>
			<key>Date Added</key><date>2017-02-20T19:48:10Z</date>
			<key>Bit Rate</key><integer>320</integer>
			<key>Sample Rate</key><integer>44100</integer>
			<key>Play Count</key><integer>1</integer>
			<key>Play Date</key><integer>3571558307</integer>
			<key>Play Date UTC</key><date>2017-03-05T19:31:47Z</date>
			<key>Skip Count</key><integer>1</integer>
			<key>Skip Date</key><date>2017-03-08T02:09:13Z</date>
			<key>Rating</key><integer>100</integer>
			<key>Album Rating</key><integer>80</integer>
			<key>Artwork Count</key><integer>1</integer>
			<key>Sort Album</key><string>Complete Recorded Works Vol 4.1 1936-1937</string>
			<key>Sort Artist</key><string>Fats Waller</string>
			<key>Persistent ID</key><string>29A8A747E0A6498E</string>
			<key>Track Type</key><string>File</string>
			<key>Location</key><string>file:///Volumes/LAVALAMP/music/iTunes/Fats%20Waller/The%20Complete%20Recorded%20Works/Vol%204%20-%201936-1938/CD%201/02%20-%20Copper%20colored%20gal.mp3</string>
			<key>File Folder Count</key><integer>6</integer>
			<key>Library Folder Count</key><integer>1</integer>
		</dict>
		<key>13069</key>
		<dict>
			<key>Track ID</key><integer>13069</integer>
			<key>Name</key><string>Shortnin' Bread</string>
			<key>Artist</key><string>Fats Waller</string>
			<key>Album</key><string>The Complete Recorded Works Vol 6.2 1940-1942</string>
			<key>Kind</key><string>MPEG audio file</string>
			<key>Size</key><integer>6960100</integer>
			<key>Total Time</key><integer>165120</integer>
			<key>Track Number</key><integer>10</integer>
			<key>Date Modified</key><date>2017-02-20T20:16:27Z</date>
			<key>Date Added</key><date>2017-02-20T19:48:10Z</date>
			<key>Bit Rate</key><integer>320</integer>
			<key>Sample Rate</key><integer>44100</integer>
			<key>Play Count</key><integer>1</integer>
			<key>Play Date</key><integer>3571380165</integer>
			<key>Play Date UTC</key><date>2017-03-03T18:02:45Z</date>
			<key>Skip Count</key><integer>1</integer>
			<key>Skip Date</key><date>2017-02-27T04:43:05Z</date>
			<key>Rating</key><integer>100</integer>
			<key>Album Rating</key><integer>60</integer>
			<key>Artwork Count</key><integer>1</integer>
			<key>Sort Album</key><string>Complete Recorded Works Vol 6.2 1940-1942</string>
			<key>Sort Artist</key><string>Fats Waller</string>
			<key>Persistent ID</key><string>64E6207AC5949AC2</string>
			<key>Track Type</key><string>File</string>
			<key>Location</key><string>file:///Volumes/LAVALAMP/music/iTunes/Fats%20Waller/The%20Complete%20Recorded%20Works/Vol%206%20-%201940-1942/CD%202/10%20-%20Shortnin'%20Bread.mp3</string>
			<key>File Folder Count</key><integer>6</integer>
			<key>Library Folder Count</key><integer>1</integer>
		</dict>
		<key>13085</key>
		<dict>
			<key>Track ID</key><integer>13085</integer>
			<key>Name</key><string>Come and Get It</string>
			<key>Artist</key><string>Fats Waller</string>
			<key>Album</key><string>The Complete Recorded Works Vol 6.3 1940-1942</string>
			<key>Kind</key><string>MPEG audio file</string>
			<key>Size</key><integer>6944593</integer>
			<key>Total Time</key><integer>164728</integer>
			<key>Track Number</key><integer>5</integer>
			<key>Date Modified</key><date>2017-02-20T20:17:00Z</date>
			<key>Date Added</key><date>2017-02-20T19:48:10Z</date>
			<key>Bit Rate</key><integer>320</integer>
			<key>Sample Rate</key><integer>44100</integer>
			<key>Play Count</key><integer>2</integer>
			<key>Play Date</key><integer>3571752563</integer>
			<key>Play Date UTC</key><date>2017-03-08T01:29:23Z</date>
			<key>Skip Count</key><integer>1</integer>
			<key>Skip Date</key><date>2017-03-08T02:03:32Z</date>
			<key>Rating</key><integer>100</integer>
			<key>Album Rating</key><integer>60</integer>
			<key>Artwork Count</key><integer>1</integer>
			<key>Sort Album</key><string>Complete Recorded Works Vol 6.3 1940-1942</string>
			<key>Sort Artist</key><string>Fats Waller</string>
			<key>Persistent ID</key><string>168A2F47CDC75755</string>
			<key>Track Type</key><string>File</string>
			<key>Location</key><string>file:///Volumes/LAVALAMP/music/iTunes/Fats%20Waller/The%20Complete%20Recorded%20Works/Vol%206%20-%201940-1942/CD%203/05%20-%20Come%20and%20Get%20It.mp3</string>
			<key>File Folder Count</key><integer>6</integer>
			<key>Library Folder Count</key><integer>1</integer>
		</dict>
		<key>13087</key>
		<dict>
			<key>Track ID</key><integer>13087</integer>
			<key>Name</key><string>Rump Steak Serenade</string>
			<key>Artist</key><string>Fats Waller</string>
			<key>Album</key><string>The Complete Recorded Works Vol 6.3 1940-1942</string>
			<key>Kind</key><string>MPEG audio file</string>
			<key>Size</key><integer>6858916</integer>
			<key>Total Time</key><integer>162586</integer>
			<key>Track Number</key><integer>6</integer>
			<key>Date Modified</key><date>2017-02-20T20:17:00Z</date>
			<key>Date Added</key><date>2017-02-20T19:48:10Z</date>
			<key>Bit Rate</key><integer>320</integer>
			<key>Sample Rate</key><integer>44100</integer>
			<key>Play Count</key><integer>2</integer>
			<key>Play Date</key><integer>3571934587</integer>
			<key>Play Date UTC</key><date>2017-03-10T04:03:07Z</date>
			<key>Rating</key><integer>100</integer>
			<key>Album Rating</key><integer>60</integer>
			<key>Artwork Count</key><integer>1</integer>
			<key>Sort Album</key><string>Complete Recorded Works Vol 6.3 1940-1942</string>
			<key>Sort Artist</key><string>Fats Waller</string>
			<key>Persistent ID</key><string>2F60AAB030C27276</string>
			<key>Track Type</key><string>File</string>
			<key>Location</key><string>file:///Volumes/LAVALAMP/music/iTunes/Fats%20Waller/The%20Complete%20Recorded%20Works/Vol%206%20-%201940-1942/CD%203/06%20-%20Rump%20Steak%20Serenade.mp3</string>
			<key>File Folder Count</key><integer>6</integer>
			<key>Library Folder Count</key><integer>1</integer>
		</dict>
		<key>13113</key>
		<dict>
			<key>Track ID</key><integer>13113</integer>
			<key>Name</key><string>You're A Viper (The Reefer Song)</string>
			<key>Artist</key><string>Fats Waller</string>
			<key>Album</key><string>The Complete Recorded Works Vol 6.4 1940-1942</string>
			<key>Kind</key><string>MPEG audio file</string>
			<key>Size</key><integer>7467332</integer>
			<key>Total Time</key><integer>177841</integer>
			<key>Track Number</key><integer>12</integer>
			<key>Date Modified</key><date>2017-02-20T20:17:27Z</date>
			<key>Date Added</key><date>2017-02-20T19:48:10Z</date>
			<key>Bit Rate</key><integer>320</integer>
			<key>Sample Rate</key><integer>44100</integer>
			<key>Play Count</key><integer>1</integer>
			<key>Play Date</key><integer>3570445532</integer>
			<key>Play Date UTC</key><date>2017-02-20T22:25:32Z</date>
			<key>Rating</key><integer>100</integer>
			<key>Album Rating</key><integer>80</integer>
			<key>Artwork Count</key><integer>1</integer>
			<key>Sort Album</key><string>Complete Recorded Works Vol 6.4 1940-1942</string>
			<key>Sort Artist</key><string>Fats Waller</string>
			<key>Persistent ID</key><string>A3C5242A79F0A0CB</string>
			<key>Track Type</key><string>File</string>
			<key>Location</key><string>file:///Volumes/LAVALAMP/music/iTunes/Fats%20Waller/The%20Complete%20Recorded%20Works/Vol%206%20-%201940-1942/CD%204/12%20-%20You're%20A%20Viper%20(The%20Reefer%20Song).mp3</string>
			<key>File Folder Count</key><integer>6</integer>
			<key>Library Folder Count</key><integer>1</integer>
		</dict>
		<key>13279</key>
		<dict>
			<key>Track ID</key><integer>13279</integer>
			<key>Name</key><string>Im Gonna Let Him Ride</string>
			<key>Artist</key><string>Helen Humes</string>
			<key>Album</key><string>YouTube</string>
			<key>Kind</key><string>MPEG audio file</string>
			<key>Size</key><integer>2588464</integer>
			<key>Total Time</key><integer>107676</integer>
			<key>Date Modified</key><date>2017-02-24T18:43:06Z</date>
			<key>Date Added</key><date>2017-02-21T07:18:43Z</date>
			<key>Bit Rate</key><integer>192</integer>
			<key>Sample Rate</key><integer>44100</integer>
			<key>Play Count</key><integer>2</integer>
			<key>Play Date</key><integer>3571917061</integer>
			<key>Play Date UTC</key><date>2017-03-09T23:11:01Z</date>
			<key>Rating</key><integer>100</integer>
			<key>Album Rating</key><integer>100</integer>
			<key>Album Rating Computed</key><true/>
			<key>Sort Album</key><string>YouTube</string>
			<key>Persistent ID</key><string>AE951BCB5D8E2007</string>
			<key>Track Type</key><string>File</string>
			<key>Location</key><string>file:///Volumes/LAVALAMP/music/iTunes/YouTube/Early%20Rock%20n'%20Roll/Helen%20Humes%20-%20Im%20Gonna%20Let%20Him%20Ride.mp3</string>
			<key>File Folder Count</key><integer>4</integer>
			<key>Library Folder Count</key><integer>1</integer>
		</dict>
		<key>13939</key>
		<dict>
			<key>Track ID</key><integer>13939</integer>
			<key>Name</key><string>Suspicion</string>
			<key>Artist</key><string>Tex Williams</string>
			<key>Album</key><string>YouTube</string>
			<key>Kind</key><string>MPEG audio file</string>
			<key>Size</key><integer>4284334</integer>
			<key>Total Time</key><integer>178337</integer>
			<key>Date Modified</key><date>2017-03-03T05:50:57Z</date>
			<key>Date Added</key><date>2017-02-23T04:37:51Z</date>
			<key>Bit Rate</key><integer>192</integer>
			<key>Sample Rate</key><integer>44100</integer>
			<key>Comments</key><string>converted by convert2mp3.net</string>
			<key>Play Count</key><integer>3</integer>
			<key>Play Date</key><integer>3571754606</integer>
			<key>Play Date UTC</key><date>2017-03-08T02:03:26Z</date>
			<key>Skip Count</key><integer>1</integer>
			<key>Skip Date</key><date>2017-02-24T00:41:29Z</date>
			<key>Rating</key><integer>100</integer>
			<key>Album Rating</key><integer>80</integer>
			<key>Sort Album</key><string>YouTube</string>
			<key>Persistent ID</key><string>AA325F01350C399C</string>
			<key>Track Type</key><string>File</string>
			<key>Location</key><string>file:///Volumes/LAVALAMP/music/iTunes/Tex%20Williams/YouTube/Tex%20Williams%20-%20Suspicion.mp3</string>
			<key>File Folder Count</key><integer>4</integer>
			<key>Library Folder Count</key><integer>1</integer>
		</dict>
		<key>13997</key>
		<dict>
			<key>Track ID</key><integer>13997</integer>
			<key>Name</key><string>Big Chief Boogie</string>
			<key>Artist</key><string>Spade Cooley</string>
			<key>Album Artist</key><string>Spade Cooley</string>
			<key>Album</key><string>Swingin' The Devil's Dream</string>
			<key>Genre</key><string>Western Swing</string>
			<key>Kind</key><string>MPEG audio file</string>
			<key>Size</key><integer>6691386</integer>
			<key>Total Time</key><integer>166008</integer>
			<key>Track Number</key><integer>11</integer>
			<key>Date Modified</key><date>2017-02-24T04:19:28Z</date>
			<key>Date Added</key><date>2017-02-24T04:18:19Z</date>
			<key>Bit Rate</key><integer>320</integer>
			<key>Sample Rate</key><integer>44100</integer>
			<key>Play Count</key><integer>8</integer>
			<key>Play Date</key><integer>3571844645</integer>
			<key>Play Date UTC</key><date>2017-03-09T03:04:05Z</date>
			<key>Release Date</key><date>2003-01-01T12:00:00Z</date>
			<key>Rating</key><integer>100</integer>
			<key>Album Rating</key><integer>60</integer>
			<key>Artwork Count</key><integer>1</integer>
			<key>Sort Album</key><string>Swingin' The Devil's Dream</string>
			<key>Persistent ID</key><string>68D14DDD11DD5DD7</string>
			<key>Track Type</key><string>File</string>
			<key>Location</key><string>file:///Volumes/LAVALAMP/music/iTunes/Spade%20Cooley/Swingin'%20The%20Devil's%20Dream%20%20%5B2%20disc%20set%5D/disc%202/11%20-%20Big%20Chief%20Boogie.mp3</string>
			<key>File Folder Count</key><integer>5</integer>
			<key>Library Folder Count</key><integer>1</integer>
		</dict>
		<key>14135</key>
		<dict>
			<key>Track ID</key><integer>14135</integer>
			<key>Name</key><string>Somebody's Been Using That Thing</string>
			<key>Artist</key><string>Milton Brown and his Brownies</string>
			<key>Kind</key><string>MPEG audio file</string>
			<key>Size</key><integer>4132614</integer>
			<key>Total Time</key><integer>172016</integer>
			<key>Date Modified</key><date>2017-02-24T05:49:15Z</date>
			<key>Date Added</key><date>2017-02-24T07:06:47Z</date>
			<key>Bit Rate</key><integer>192</integer>
			<key>Sample Rate</key><integer>44100</integer>
			<key>Comments</key><string>converted by convert2mp3.net</string>
			<key>Rating</key><integer>100</integer>
			<key>Album Rating</key><integer>100</integer>
			<key>Album Rating Computed</key><true/>
			<key>Persistent ID</key><string>51690FA17A4CDEA3</string>
			<key>Track Type</key><string>File</string>
			<key>Location</key><string>file:///Volumes/LAVALAMP/music/iTunes/Milton%20Brown%20and%20His%20Musical%20Brownies/YouTube/Milton%20Brown%20and%20his%20Brownies%20-%20Somebody's%20Been%20Using%20That%20Thing.mp3</string>
			<key>File Folder Count</key><integer>4</integer>
			<key>Library Folder Count</key><integer>1</integer>
		</dict>
		<key>14171</key>
		<dict>
			<key>Track ID</key><integer>14171</integer>
			<key>Name</key><string>Cocaine Blues (1948)</string>
			<key>Artist</key><string>Roy Hogsed</string>
			<key>Kind</key><string>MPEG audio file</string>
			<key>Size</key><integer>3732001</integer>
			<key>Total Time</key><integer>155324</integer>
			<key>Date Modified</key><date>2017-02-24T06:33:14Z</date>
			<key>Date Added</key><date>2017-02-24T07:09:10Z</date>
			<key>Bit Rate</key><integer>192</integer>
			<key>Sample Rate</key><integer>44100</integer>
			<key>Comments</key><string>converted by convert2mp3.net</string>
			<key>Play Count</key><integer>2</integer>
			<key>Play Date</key><integer>3571233608</integer>
			<key>Play Date UTC</key><date>2017-03-02T01:20:08Z</date>
			<key>Skip Count</key><integer>2</integer>
			<key>Skip Date</key><date>2017-03-08T02:03:37Z</date>
			<key>Rating</key><integer>100</integer>
			<key>Album Rating</key><integer>100</integer>
			<key>Persistent ID</key><string>D35B345C79937D74</string>
			<key>Track Type</key><string>File</string>
			<key>Location</key><string>file:///Volumes/LAVALAMP/music/iTunes/YouTube/Western%20Swing%20misc/Roy%20Hogsed%20-%20Cocaine%20Blues%20(1948).mp3</string>
			<key>File Folder Count</key><integer>4</integer>
			<key>Library Folder Count</key><integer>1</integer>
		</dict>
		<key>14753</key>
		<dict>
			<key>Track ID</key><integer>14753</integer>
			<key>Name</key><string>49 Women</string>
			<key>Artist</key><string>Pee Wee King and His Golden West Cowboys</string>
			<key>Album</key><string>YouTube</string>
			<key>Kind</key><string>MPEG audio file</string>
			<key>Size</key><integer>3614763</integer>
			<key>Total Time</key><integer>150439</integer>
			<key>Date Modified</key><date>2017-03-03T07:45:59Z</date>
			<key>Date Added</key><date>2017-03-03T07:45:33Z</date>
			<key>Bit Rate</key><integer>192</integer>
			<key>Sample Rate</key><integer>44100</integer>
			<key>Play Count</key><integer>2</integer>
			<key>Play Date</key><integer>3571751959</integer>
			<key>Play Date UTC</key><date>2017-03-08T01:19:19Z</date>
			<key>Rating</key><integer>100</integer>
			<key>Album Rating</key><integer>100</integer>
			<key>Album Rating Computed</key><true/>
			<key>Persistent ID</key><string>363F35E3547C5411</string>
			<key>Track Type</key><string>File</string>
			<key>Location</key><string>file:///Volumes/LAVALAMP/music/iTunes/Pee%20Wee%20King/YouTube/Pee%20Wee%20King%20and%20His%20Golden%20West%20Cowboys%20-%2049%20Women.mp3</string>
			<key>File Folder Count</key><integer>4</integer>
			<key>Library Folder Count</key><integer>1</integer>
		</dict>
		<key>14759</key>
		<dict>
			<key>Track ID</key><integer>14759</integer>
			<key>Name</key><string>Squaws Along The Yukon</string>
			<key>Artist</key><string>Hank Thompson</string>
			<key>Album</key><string>YouTube</string>
			<key>Kind</key><string>MPEG audio file</string>
			<key>Size</key><integer>3752690</integer>
			<key>Total Time</key><integer>156186</integer>
			<key>Date Modified</key><date>2017-03-03T07:53:59Z</date>
			<key>Date Added</key><date>2017-03-03T07:53:19Z</date>
			<key>Bit Rate</key><integer>192</integer>
			<key>Sample Rate</key><integer>44100</integer>
			<key>Play Count</key><integer>1</integer>
			<key>Play Date</key><integer>3571357805</integer>
			<key>Play Date UTC</key><date>2017-03-03T11:50:05Z</date>
			<key>Rating</key><integer>100</integer>
			<key>Album Rating</key><integer>100</integer>
			<key>Album Rating Computed</key><true/>
			<key>Sort Album</key><string>YouTube</string>
			<key>Persistent ID</key><string>F9F14D4AD3DD6692</string>
			<key>Track Type</key><string>File</string>
			<key>Location</key><string>file:///Volumes/LAVALAMP/music/iTunes/Hank%20Thompson/YouTube/Hank%20Thompson%20-%20Squaws%20Along%20The%20Yukon.mp3</string>
			<key>File Folder Count</key><integer>4</integer>
			<key>Library Folder Count</key><integer>1</integer>
		</dict>
		<key>14763</key>
		<dict>
			<key>Track ID</key><integer>14763</integer>
			<key>Name</key><string>I Want To Learn To Do It</string>
			<key>Artist</key><string>T Texas Tyler</string>
			<key>Album</key><string>YouTube</string>
			<key>Kind</key><string>MPEG audio file</string>
			<key>Size</key><integer>4096252</integer>
			<key>Total Time</key><integer>170501</integer>
			<key>Date Modified</key><date>2017-03-03T07:56:28Z</date>
			<key>Date Added</key><date>2017-03-03T07:56:06Z</date>
			<key>Bit Rate</key><integer>192</integer>
			<key>Sample Rate</key><integer>44100</integer>
			<key>Play Count</key><integer>1</integer>
			<key>Play Date</key><integer>3571751809</integer>
			<key>Play Date UTC</key><date>2017-03-08T01:16:49Z</date>
			<key>Skip Count</key><integer>2</integer>
			<key>Skip Date</key><date>2017-03-10T04:00:26Z</date>
			<key>Rating</key><integer>100</integer>
			<key>Album Rating</key><integer>100</integer>
			<key>Album Rating Computed</key><true/>
			<key>Persistent ID</key><string>6CD602D303B38A10</string>
			<key>Track Type</key><string>File</string>
			<key>Location</key><string>file:///Volumes/LAVALAMP/music/iTunes/YouTube/Western%20Swing%20misc/T%20Texas%20Tyler%20-%20I%20Want%20To%20Learn%20To%20Do%20It.mp3</string>
			<key>File Folder Count</key><integer>4</integer>
			<key>Library Folder Count</key><integer>1</integer>
		</dict>
		<key>14773</key>
		<dict>
			<key>Track ID</key><integer>14773</integer>
			<key>Name</key><string>I'm No Communist</string>
			<key>Artist</key><string>Carson Robison</string>
			<key>Album</key><string>YouTube</string>
			<key>Kind</key><string>MPEG audio file</string>
			<key>Size</key><integer>4046097</integer>
			<key>Total Time</key><integer>168411</integer>
			<key>Date Modified</key><date>2017-03-03T07:56:28Z</date>
			<key>Date Added</key><date>2017-03-03T07:56:06Z</date>
			<key>Bit Rate</key><integer>192</integer>
			<key>Sample Rate</key><integer>44100</integer>
			<key>Play Count</key><integer>1</integer>
			<key>Play Date</key><integer>3571559745</integer>
			<key>Play Date UTC</key><date>2017-03-05T19:55:45Z</date>
			<key>Rating</key><integer>100</integer>
			<key>Album Rating</key><integer>100</integer>
			<key>Album Rating Computed</key><true/>
			<key>Persistent ID</key><string>CE1FBB4DC0CB4771</string>
			<key>Track Type</key><string>File</string>
			<key>Location</key><string>file:///Volumes/LAVALAMP/music/iTunes/YouTube/Western%20Swing%20misc/Carson%20Robison%20-%20I'm%20No%20Communist.mp3</string>
			<key>File Folder Count</key><integer>4</integer>
			<key>Library Folder Count</key><integer>1</integer>
		</dict>
		<key>14921</key>
		<dict>
			<key>Track ID</key><integer>14921</integer>
			<key>Name</key><string>Big Long Slidin' Thing (1954)</string>
			<key>Artist</key><string>Dinah Washington</string>
			<key>Album</key><string>YouTube</string>
			<key>Kind</key><string>MPEG audio file</string>
			<key>Size</key><integer>4198443</integer>
			<key>Total Time</key><integer>174759</integer>
			<key>Year</key><integer>1954</integer>
			<key>Date Modified</key><date>2017-03-05T07:01:00Z</date>
			<key>Date Added</key><date>2017-03-05T06:56:14Z</date>
			<key>Bit Rate</key><integer>192</integer>
			<key>Sample Rate</key><integer>44100</integer>
			<key>Play Count</key><integer>1</integer>
			<key>Play Date</key><integer>3571753154</integer>
			<key>Play Date UTC</key><date>2017-03-08T01:39:14Z</date>
			<key>Skip Count</key><integer>1</integer>
			<key>Skip Date</key><date>2017-03-08T02:06:18Z</date>
			<key>Rating</key><integer>100</integer>
			<key>Album Rating</key><integer>100</integer>
			<key>Album Rating Computed</key><true/>
			<key>Sort Album</key><string>YouTube</string>
			<key>Persistent ID</key><string>171FF7ACD2736FB5</string>
			<key>Track Type</key><string>File</string>
			<key>Location</key><string>file:///Volumes/LAVALAMP/music/iTunes/YouTube/Early%20Boogie%20Woogie/Dinah%20Washington%20-%20Big%20Long%20Slidin'%20Thing%20(1954).mp3</string>
			<key>File Folder Count</key><integer>4</integer>
			<key>Library Folder Count</key><integer>1</integer>
		</dict>
		<key>14927</key>
		<dict>
			<key>Track ID</key><integer>14927</integer>
			<key>Name</key><string>Drank Up All The Wine Last Night (1949)</string>
			<key>Artist</key><string>Stick McGhee</string>
			<key>Album</key><string>YouTube</string>
			<key>Kind</key><string>MPEG audio file</string>
			<key>Size</key><integer>4479312</integer>
			<key>Total Time</key><integer>186462</integer>
			<key>Year</key><integer>1949</integer>
			<key>Date Modified</key><date>2017-03-05T07:01:49Z</date>
			<key>Date Added</key><date>2017-03-05T06:56:14Z</date>
			<key>Bit Rate</key><integer>192</integer>
			<key>Sample Rate</key><integer>44100</integer>
			<key>Play Count</key><integer>2</integer>
			<key>Play Date</key><integer>3571751300</integer>
			<key>Play Date UTC</key><date>2017-03-08T01:08:20Z</date>
			<key>Skip Count</key><integer>1</integer>
			<key>Skip Date</key><date>2017-03-08T02:06:15Z</date>
			<key>Rating</key><integer>100</integer>
			<key>Album Rating</key><integer>100</integer>
			<key>Album Rating Computed</key><true/>
			<key>Sort Album</key><string>YouTube</string>
			<key>Persistent ID</key><string>4BA47512BCC62DB8</string>
			<key>Track Type</key><string>File</string>
			<key>Location</key><string>file:///Volumes/LAVALAMP/music/iTunes/YouTube/Early%20Boogie%20Woogie/Stick%20McGhee%20-%20Drank%20Up%20All%20The%20Wine%20Last%20Night%20(1949).mp3</string>
			<key>File Folder Count</key><integer>4</integer>
			<key>Library Folder Count</key><integer>1</integer>
		</dict>
		<key>14973</key>
		<dict>
			<key>Track ID</key><integer>14973</integer>
			<key>Name</key><string>Hula Blues</string>
			<key>Artist</key><string>Jim &#38; Bob, The Genial Hawaiians</string>
			<key>Album Artist</key><string>Various Artists</string>
			<key>Album</key><string>Vintage Hawaiian Music: Steel Guitar Masters 1928-1934</string>
			<key>Kind</key><string>MPEG audio file</string>
			<key>Size</key><integer>3991174</integer>
			<key>Total Time</key><integer>163004</integer>
			<key>Track Number</key><integer>15</integer>
			<key>Track Count</key><integer>15</integer>
			<key>Year</key><integer>1992</integer>
			<key>Date Modified</key><date>2017-03-06T01:44:28Z</date>
			<key>Date Added</key><date>2017-03-05T19:12:11Z</date>
			<key>Bit Rate</key><integer>192</integer>
			<key>Sample Rate</key><integer>44100</integer>
			<key>Comments</key><string>[mudmashers]</string>
			<key>Play Count</key><integer>1</integer>
			<key>Play Date</key><integer>3571663906</integer>
			<key>Play Date UTC</key><date>2017-03-07T00:51:46Z</date>
			<key>Rating</key><integer>100</integer>
			<key>Album Rating</key><integer>60</integer>
			<key>Artwork Count</key><integer>1</integer>
			<key>Persistent ID</key><string>1D67C54C82E6B67F</string>
			<key>Track Type</key><string>File</string>
			<key>Location</key><string>file:///Volumes/LAVALAMP/music/iTunes/Vintage%20Hawaiian%20Music%20-%20Steel%20Guitar%20Masters%201928-34/15%20-%20Hula%20Blues%20-%20Jim%20&#38;%20Bob,%20The%20Genial%20Hawaiians.mp3</string>
			<key>File Folder Count</key><integer>3</integer>
			<key>Library Folder Count</key><integer>1</integer>
		</dict>
		<key>15043</key>
		<dict>
			<key>Track ID</key><integer>15043</integer>
			<key>Name</key><string>61. So Round, So Firm, So Fully Packed (1947)</string>
			<key>Artist</key><string>Ernest Tubb</string>
			<key>Album</key><string>Steelin' It- The Steel Guitar Story</string>
			<key>Kind</key><string>MPEG audio file</string>
			<key>Size</key><integer>7659857</integer>
			<key>Total Time</key><integer>174837</integer>
			<key>Year</key><integer>1947</integer>
			<key>Date Modified</key><date>2017-03-06T01:05:07Z</date>
			<key>Date Added</key><date>2017-03-05T20:37:02Z</date>
			<key>Bit Rate</key><integer>320</integer>
			<key>Sample Rate</key><integer>44100</integer>
			<key>Play Count</key><integer>2</integer>
			<key>Play Date</key><integer>3571564620</integer>
			<key>Play Date UTC</key><date>2017-03-05T21:17:00Z</date>
			<key>Skip Count</key><integer>1</integer>
			<key>Skip Date</key><date>2017-03-08T02:06:23Z</date>
			<key>Rating</key><integer>100</integer>
			<key>Album Rating</key><integer>80</integer>
			<key>Artwork Count</key><integer>1</integer>
			<key>Sort Album</key><string>Steelin' It- The Steel Guitar Story</string>
			<key>Sort Artist</key><string>Ernest Tubb</string>
			<key>Persistent ID</key><string>967BE667792D8956</string>
			<key>Track Type</key><string>File</string>
			<key>Location</key><string>file:///Volumes/LAVALAMP/music/iTunes/Steelin'%20It-%20The%20Steel%20Guitar%20Story%20-%204CD-BOX/61.%20So%20Round,%20So%20Firm,%20So%20Fully%20Packed.mp3</string>
			<key>File Folder Count</key><integer>3</integer>
			<key>Library Folder Count</key><integer>1</integer>
		</dict>
		<key>15137</key>
		<dict>
			<key>Track ID</key><integer>15137</integer>
			<key>Name</key><string>Let Me Play With Your Poodle</string>
			<key>Artist</key><string>Hank Penny</string>
			<key>Album</key><string>YouTube</string>
			<key>Kind</key><string>MPEG audio file</string>
			<key>Size</key><integer>4056604</integer>
			<key>Total Time</key><integer>166217</integer>
			<key>Date Modified</key><date>2017-03-11T16:17:26Z</date>
			<key>Date Added</key><date>2017-03-07T06:45:14Z</date>
			<key>Bit Rate</key><integer>192</integer>
			<key>Sample Rate</key><integer>44100</integer>
			<key>Play Count</key><integer>2</integer>
			<key>Play Date</key><integer>3571841909</integer>
			<key>Play Date UTC</key><date>2017-03-09T02:18:29Z</date>
			<key>Rating</key><integer>100</integer>
			<key>Album Rating</key><integer>100</integer>
			<key>Album Rating Computed</key><true/>
			<key>Artwork Count</key><integer>1</integer>
			<key>Sort Album</key><string>YouTube</string>
			<key>Persistent ID</key><string>CC6E32D7F943F16B</string>
			<key>Track Type</key><string>File</string>
			<key>Location</key><string>file:///Volumes/LAVALAMP/music/iTunes/Hank%20Penny/YouTube/Hank%20Penny%20-%20Let%20Me%20Play%20With%20Your%20Poodle.mp3</string>
			<key>File Folder Count</key><integer>4</integer>
			<key>Library Folder Count</key><integer>1</integer>
		</dict>
		<key>15157</key>
		<dict>
			<key>Track ID</key><integer>15157</integer>
			<key>Name</key><string>My Girl's Pussy (1931)</string>
			<key>Artist</key><string>Harry Roy &#38; His Orchestra</string>
			<key>Album</key><string>YouTube</string>
			<key>Kind</key><string>MPEG audio file</string>
			<key>Size</key><integer>4689963</integer>
			<key>Total Time</key><integer>195239</integer>
			<key>Year</key><integer>1931</integer>
			<key>Date Modified</key><date>2017-03-07T06:52:09Z</date>
			<key>Date Added</key><date>2017-03-07T06:56:35Z</date>
			<key>Bit Rate</key><integer>192</integer>
			<key>Sample Rate</key><integer>44100</integer>
			<key>Comments</key><string>converted by convert2mp3.net</string>
			<key>Skip Count</key><integer>1</integer>
			<key>Skip Date</key><date>2017-03-08T02:09:18Z</date>
			<key>Rating</key><integer>100</integer>
			<key>Album Rating</key><integer>100</integer>
			<key>Album Rating Computed</key><true/>
			<key>Sort Album</key><string>YouTube</string>
			<key>Sort Name</key><string>My Girl's Pussy (1931)</string>
			<key>Persistent ID</key><string>4A6315639B3B6192</string>
			<key>Track Type</key><string>File</string>
			<key>Location</key><string>file:///Volumes/LAVALAMP/music/iTunes/YouTube/Naughty/Harry%20Roy%20&#38;%20His%20Orchestra%20-%20My%20Girls%20Pussy%20(1931).mp3</string>
			<key>File Folder Count</key><integer>4</integer>
			<key>Library Folder Count</key><integer>1</integer>
		</dict>
		<key>15159</key>
		<dict>
			<key>Track ID</key><integer>15159</integer>
			<key>Name</key><string>Shave Me Dry (1935)</string>
			<key>Artist</key><string>Lucille Bogan (aka Bessie Jackson)</string>
			<key>Album</key><string>YouTube</string>
			<key>Kind</key><string>MPEG audio file</string>
			<key>Size</key><integer>4836040</integer>
			<key>Total Time</key><integer>201325</integer>
			<key>Year</key><integer>1935</integer>
			<key>Date Modified</key><date>2017-03-07T06:49:55Z</date>
			<key>Date Added</key><date>2017-03-07T06:56:35Z</date>
			<key>Bit Rate</key><integer>192</integer>
			<key>Sample Rate</key><integer>44100</integer>
			<key>Comments</key><string>converted by convert2mp3.net</string>
			<key>Rating</key><integer>100</integer>
			<key>Album Rating</key><integer>100</integer>
			<key>Album Rating Computed</key><true/>
			<key>Sort Album</key><string>YouTube</string>
			<key>Persistent ID</key><string>7B575688476193FB</string>
			<key>Track Type</key><string>File</string>
			<key>Location</key><string>file:///Volumes/LAVALAMP/music/iTunes/YouTube/Naughty/Lucille%20Bogan%20(aka%20Bessie%20Jackson)%20-%20Shave%20Me%20Dry%20(1935).mp3</string>
			<key>File Folder Count</key><integer>4</integer>
			<key>Library Folder Count</key><integer>1</integer>
		</dict>
		<key>15161</key>
		<dict>
			<key>Track ID</key><integer>15161</integer>
			<key>Name</key><string>Rabbits Don't Ever Get Married</string>
			<key>Artist</key><string>Hank Penny</string>
			<key>Album</key><string>YouTube</string>
			<key>Kind</key><string>MPEG audio file</string>
			<key>Size</key><integer>3903676</integer>
			<key>Total Time</key><integer>159843</integer>
			<key>Date Modified</key><date>2017-03-11T16:17:28Z</date>
			<key>Date Added</key><date>2017-03-07T07:01:26Z</date>
			<key>Bit Rate</key><integer>192</integer>
			<key>Sample Rate</key><integer>44100</integer>
			<key>Comments</key><string>converted by convert2mp3.net</string>
			<key>Play Count</key><integer>1</integer>
			<key>Play Date</key><integer>3571750943</integer>
			<key>Play Date UTC</key><date>2017-03-08T01:02:23Z</date>
			<key>Skip Count</key><integer>1</integer>
			<key>Skip Date</key><date>2017-03-08T02:00:27Z</date>
			<key>Rating</key><integer>100</integer>
			<key>Album Rating</key><integer>100</integer>
			<key>Album Rating Computed</key><true/>
			<key>Artwork Count</key><integer>1</integer>
			<key>Sort Album</key><string>YouTube</string>
			<key>Persistent ID</key><string>256A34BF353F5048</string>
			<key>Track Type</key><string>File</string>
			<key>Location</key><string>file:///Volumes/LAVALAMP/music/iTunes/Hank%20Penny/YouTube/Hank%20Penny%20-%20Rabbits%20Don't%20Ever%20Get%20Married.mp3</string>
			<key>File Folder Count</key><integer>4</integer>
			<key>Library Folder Count</key><integer>1</integer>
		</dict>
		<key>15163</key>
		<dict>
			<key>Track ID</key><integer>15163</integer>
			<key>Name</key><string>You're Bound to Look Like a Monkey</string>
			<key>Artist</key><string>Hank Penny</string>
			<key>Album</key><string>YouTube</string>
			<key>Kind</key><string>MPEG audio file</string>
			<key>Size</key><integer>3355066</integer>
			<key>Total Time</key><integer>136986</integer>
			<key>Date Modified</key><date>2017-03-11T16:17:29Z</date>
			<key>Date Added</key><date>2017-03-07T07:03:38Z</date>
			<key>Bit Rate</key><integer>192</integer>
			<key>Sample Rate</key><integer>44100</integer>
			<key>Rating</key><integer>100</integer>
			<key>Album Rating</key><integer>100</integer>
			<key>Album Rating Computed</key><true/>
			<key>Artwork Count</key><integer>1</integer>
			<key>Sort Album</key><string>YouTube</string>
			<key>Persistent ID</key><string>F394B044BBC60895</string>
			<key>Track Type</key><string>File</string>
			<key>Location</key><string>file:///Volumes/LAVALAMP/music/iTunes/Hank%20Penny/YouTube/Hank%20Penny%20-%20You're%20Bound%20to%20Look%20Like%20a%20Monkey.mp3</string>
			<key>File Folder Count</key><integer>4</integer>
			<key>Library Folder Count</key><integer>1</integer>
		</dict>
		<key>15165</key>
		<dict>
			<key>Track ID</key><integer>15165</integer>
			<key>Name</key><string>No Muss, No Fuss, No Bother</string>
			<key>Artist</key><string>Hank Penny</string>
			<key>Album</key><string>YouTube</string>
			<key>Kind</key><string>MPEG audio file</string>
			<key>Size</key><integer>4214008</integer>
			<key>Total Time</key><integer>172773</integer>
			<key>Date Modified</key><date>2017-03-11T16:17:27Z</date>
			<key>Date Added</key><date>2017-03-07T07:07:33Z</date>
			<key>Bit Rate</key><integer>192</integer>
			<key>Sample Rate</key><integer>44100</integer>
			<key>Comments</key><string>converted by convert2mp3.net</string>
			<key>Rating</key><integer>100</integer>
			<key>Album Rating</key><integer>100</integer>
			<key>Album Rating Computed</key><true/>
			<key>Artwork Count</key><integer>1</integer>
			<key>Sort Album</key><string>YouTube</string>
			<key>Persistent ID</key><string>488FE8DBF1D0A00E</string>
			<key>Track Type</key><string>File</string>
			<key>Location</key><string>file:///Volumes/LAVALAMP/music/iTunes/Hank%20Penny/YouTube/Hank%20Penny%20-%20No%20Muss_%20No%20Fuss_%20No%20Bother.mp3</string>
			<key>File Folder Count</key><integer>4</integer>
			<key>Library Folder Count</key><integer>1</integer>
		</dict>
		<key>15167</key>
		<dict>
			<key>Track ID</key><integer>15167</integer>
			<key>Name</key><string>The Strong Black Man</string>
			<key>Artist</key><string>Hank Penny</string>
			<key>Album</key><string>YouTube</string>
			<key>Kind</key><string>MPEG audio file</string>
			<key>Size</key><integer>4623976</integer>
			<key>Total Time</key><integer>189857</integer>
			<key>Date Modified</key><date>2017-03-11T16:17:28Z</date>
			<key>Date Added</key><date>2017-03-07T07:09:32Z</date>
			<key>Bit Rate</key><integer>192</integer>
			<key>Sample Rate</key><integer>44100</integer>
			<key>Skip Count</key><integer>1</integer>
			<key>Skip Date</key><date>2017-03-08T01:56:18Z</date>
			<key>Rating</key><integer>100</integer>
			<key>Album Rating</key><integer>100</integer>
			<key>Album Rating Computed</key><true/>
			<key>Artwork Count</key><integer>1</integer>
			<key>Sort Album</key><string>YouTube</string>
			<key>Sort Name</key><string>Strong Black Man</string>
			<key>Persistent ID</key><string>08EC3F805C7AD54C</string>
			<key>Track Type</key><string>File</string>
			<key>Location</key><string>file:///Volumes/LAVALAMP/music/iTunes/Hank%20Penny/YouTube/Hank%20Penny%20-%20The%20Strong%20Black%20Man.mp3</string>
			<key>File Folder Count</key><integer>4</integer>
			<key>Library Folder Count</key><integer>1</integer>
		</dict>
		<key>15171</key>
		<dict>
			<key>Track ID</key><integer>15171</integer>
			<key>Name</key><string>Wham! Bam! Thank You Ma'am!</string>
			<key>Artist</key><string>Hank Penny</string>
			<key>Album</key><string>YouTube</string>
			<key>Kind</key><string>MPEG audio file</string>
			<key>Size</key><integer>4390761</integer>
			<key>Total Time</key><integer>180140</integer>
			<key>Date Modified</key><date>2017-03-11T16:17:29Z</date>
			<key>Date Added</key><date>2017-03-07T07:14:14Z</date>
			<key>Bit Rate</key><integer>192</integer>
			<key>Sample Rate</key><integer>44100</integer>
			<key>Play Count</key><integer>1</integer>
			<key>Play Date</key><integer>3571750783</integer>
			<key>Play Date UTC</key><date>2017-03-08T00:59:43Z</date>
			<key>Rating</key><integer>100</integer>
			<key>Album Rating</key><integer>100</integer>
			<key>Album Rating Computed</key><true/>
			<key>Artwork Count</key><integer>1</integer>
			<key>Sort Album</key><string>YouTube</string>
			<key>Persistent ID</key><string>33F14910C27DDDBE</string>
			<key>Track Type</key><string>File</string>
			<key>Location</key><string>file:///Volumes/LAVALAMP/music/iTunes/Hank%20Penny/YouTube/Hank%20Penny%20-%20Wham!%20Bam!%20Thank%20You%20Ma'am!.mp3</string>
			<key>File Folder Count</key><integer>4</integer>
			<key>Library Folder Count</key><integer>1</integer>
		</dict>
		<key>15173</key>
		<dict>
			<key>Track ID</key><integer>15173</integer>
			<key>Name</key><string>Bloodshot Eyes</string>
			<key>Artist</key><string>Hank Penny</string>
			<key>Album</key><string>YouTube</string>
			<key>Kind</key><string>MPEG audio file</string>
			<key>Size</key><integer>3790141</integer>
			<key>Total Time</key><integer>155115</integer>
			<key>Date Modified</key><date>2017-03-11T16:17:25Z</date>
			<key>Date Added</key><date>2017-03-07T07:19:57Z</date>
			<key>Bit Rate</key><integer>192</integer>
			<key>Sample Rate</key><integer>44100</integer>
			<key>Skip Count</key><integer>1</integer>
			<key>Skip Date</key><date>2017-03-08T02:04:32Z</date>
			<key>Rating</key><integer>100</integer>
			<key>Album Rating</key><integer>100</integer>
			<key>Album Rating Computed</key><true/>
			<key>Artwork Count</key><integer>1</integer>
			<key>Sort Album</key><string>YouTube</string>
			<key>Persistent ID</key><string>C2D4AFC6B60F40AF</string>
			<key>Track Type</key><string>File</string>
			<key>Location</key><string>file:///Volumes/LAVALAMP/music/iTunes/Hank%20Penny/YouTube/Hank%20Penny%20-%20Bloodshot%20Eyes.mp3</string>
			<key>File Folder Count</key><integer>4</integer>
			<key>Library Folder Count</key><integer>1</integer>
		</dict>
		<key>15179</key>
		<dict>
			<key>Track ID</key><integer>15179</integer>
			<key>Name</key><string>They're All Just The Same To Me (1938)</string>
			<key>Artist</key><string>Hank Penny &#38; His Radio Cowboys</string>
			<key>Album</key><string>YouTube</string>
			<key>Kind</key><string>MPEG audio file</string>
			<key>Size</key><integer>4052261</integer>
			<key>Total Time</key><integer>166034</integer>
			<key>Year</key><integer>1938</integer>
			<key>Date Modified</key><date>2017-03-11T16:17:30Z</date>
			<key>Date Added</key><date>2017-03-07T07:28:32Z</date>
			<key>Bit Rate</key><integer>192</integer>
			<key>Sample Rate</key><integer>44100</integer>
			<key>Play Count</key><integer>1</integer>
			<key>Play Date</key><integer>3571752161</integer>
			<key>Play Date UTC</key><date>2017-03-08T01:22:41Z</date>
			<key>Rating</key><integer>100</integer>
			<key>Album Rating</key><integer>100</integer>
			<key>Album Rating Computed</key><true/>
			<key>Artwork Count</key><integer>1</integer>
			<key>Sort Album</key><string>YouTube</string>
			<key>Persistent ID</key><string>DF2FD7E0E5302928</string>
			<key>Track Type</key><string>File</string>
			<key>Location</key><string>file:///Volumes/LAVALAMP/music/iTunes/Hank%20Penny/YouTube/Hank%20Penny%20&#38;%20His%20Radio%20Cowboys%20-%20They're%20All%20Just%20The%20Same%20To%20Me%20(1938).mp3</string>
			<key>File Folder Count</key><integer>4</integer>
			<key>Library Folder Count</key><integer>1</integer>
		</dict>
		<key>15181</key>
		<dict>
			<key>Track ID</key><integer>15181</integer>
			<key>Name</key><string>Catch 'Em Young Treat 'Em Rough (1951)</string>
			<key>Artist</key><string>Hank Penny &#38; His Radio Cowboys</string>
			<key>Album</key><string>YouTube</string>
			<key>Kind</key><string>MPEG audio file</string>
			<key>Size</key><integer>3703057</integer>
			<key>Total Time</key><integer>151484</integer>
			<key>Year</key><integer>1951</integer>
			<key>Date Modified</key><date>2017-03-11T16:17:29Z</date>
			<key>Date Added</key><date>2017-03-07T07:32:07Z</date>
			<key>Bit Rate</key><integer>192</integer>
			<key>Sample Rate</key><integer>44100</integer>
			<key>Rating</key><integer>100</integer>
			<key>Album Rating</key><integer>100</integer>
			<key>Album Rating Computed</key><true/>
			<key>Artwork Count</key><integer>1</integer>
			<key>Sort Album</key><string>YouTube</string>
			<key>Persistent ID</key><string>24B06442D2D3C731</string>
			<key>Track Type</key><string>File</string>
			<key>Location</key><string>file:///Volumes/LAVALAMP/music/iTunes/Hank%20Penny/YouTube/Hank%20Penny%20&#38;%20His%20Radio%20Cowboys%20-%20Catch%20'Em%20Young%20Treat%20'Em%20Rough%20(1951).mp3</string>
			<key>File Folder Count</key><integer>4</integer>
			<key>Library Folder Count</key><integer>1</integer>
		</dict>
		<key>15185</key>
		<dict>
			<key>Track ID</key><integer>15185</integer>
			<key>Name</key><string>Please Warm My Weiner (1934)</string>
			<key>Artist</key><string>Bo Carter</string>
			<key>Album</key><string>YouTube</string>
			<key>Kind</key><string>MPEG audio file</string>
			<key>Size</key><integer>4304396</integer>
			<key>Total Time</key><integer>179173</integer>
			<key>Year</key><integer>1934</integer>
			<key>Date Modified</key><date>2017-03-07T07:39:58Z</date>
			<key>Date Added</key><date>2017-03-07T07:39:16Z</date>
			<key>Bit Rate</key><integer>192</integer>
			<key>Sample Rate</key><integer>44100</integer>
			<key>Rating</key><integer>100</integer>
			<key>Album Rating</key><integer>100</integer>
			<key>Album Rating Computed</key><true/>
			<key>Sort Album</key><string>YouTube</string>
			<key>Persistent ID</key><string>C1878DC5C7952762</string>
			<key>Track Type</key><string>File</string>
			<key>Location</key><string>file:///Volumes/LAVALAMP/music/iTunes/YouTube/Naughty/Bo%20Carter%20-%20Please%20Warm%20My%20Weiner%20(1934).mp3</string>
			<key>File Folder Count</key><integer>4</integer>
			<key>Library Folder Count</key><integer>1</integer>
		</dict>
		<key>15187</key>
		<dict>
			<key>Track ID</key><integer>15187</integer>
			<key>Name</key><string>Whats That Smells Like Fish (1938)</string>
			<key>Artist</key><string>Blind Boy Fuller</string>
			<key>Album</key><string>YouTube</string>
			<key>Kind</key><string>MPEG audio file</string>
			<key>Size</key><integer>3930322</integer>
			<key>Total Time</key><integer>163160</integer>
			<key>Year</key><integer>1938</integer>
			<key>Date Modified</key><date>2017-03-07T07:40:07Z</date>
			<key>Date Added</key><date>2017-03-07T07:39:16Z</date>
			<key>Bit Rate</key><integer>192</integer>
			<key>Sample Rate</key><integer>44100</integer>
			<key>Rating</key><integer>100</integer>
			<key>Album Rating</key><integer>100</integer>
			<key>Album Rating Computed</key><true/>
			<key>Sort Album</key><string>YouTube</string>
			<key>Persistent ID</key><string>2C382B664E5B1249</string>
			<key>Track Type</key><string>File</string>
			<key>Location</key><string>file:///Volumes/LAVALAMP/music/iTunes/YouTube/Naughty/Blind%20Boy%20Fuller%20-%20Whats%20That%20Smells%20Like%20Fish%20(1938).mp3</string>
			<key>File Folder Count</key><integer>4</integer>
			<key>Library Folder Count</key><integer>1</integer>
		</dict>
		<key>15189</key>
		<dict>
			<key>Track ID</key><integer>15189</integer>
			<key>Name</key><string>Rotten Cocksuckers Ball (1954)</string>
			<key>Artist</key><string>The Clovers</string>
			<key>Album</key><string>YouTube</string>
			<key>Kind</key><string>MPEG audio file</string>
			<key>Size</key><integer>2019205</integer>
			<key>Total Time</key><integer>83696</integer>
			<key>Year</key><integer>1954</integer>
			<key>Date Modified</key><date>2017-03-07T07:43:47Z</date>
			<key>Date Added</key><date>2017-03-07T07:43:31Z</date>
			<key>Bit Rate</key><integer>192</integer>
			<key>Sample Rate</key><integer>44100</integer>
			<key>Skip Count</key><integer>1</integer>
			<key>Skip Date</key><date>2017-03-08T02:03:35Z</date>
			<key>Rating</key><integer>100</integer>
			<key>Album Rating</key><integer>100</integer>
			<key>Album Rating Computed</key><true/>
			<key>Sort Artist</key><string>Clovers</string>
			<key>Persistent ID</key><string>AE5FDF914B0E260C</string>
			<key>Track Type</key><string>File</string>
			<key>Location</key><string>file:///Volumes/LAVALAMP/music/iTunes/YouTube/Naughty/The%20Clovers%20-%20Rotten%20Cocksuckers%20Ball%20(1954).mp3</string>
			<key>File Folder Count</key><integer>4</integer>
			<key>Library Folder Count</key><integer>1</integer>
		</dict>
		<key>15191</key>
		<dict>
			<key>Track ID</key><integer>15191</integer>
			<key>Name</key><string>It Ain't the Meat (1951)</string>
			<key>Artist</key><string>The Swallows</string>
			<key>Album</key><string>YouTube</string>
			<key>Kind</key><string>MPEG audio file</string>
			<key>Size</key><integer>3760652</integer>
			<key>Total Time</key><integer>156133</integer>
			<key>Year</key><integer>1951</integer>
			<key>Date Modified</key><date>2017-03-07T07:46:12Z</date>
			<key>Date Added</key><date>2017-03-07T07:45:43Z</date>
			<key>Bit Rate</key><integer>192</integer>
			<key>Sample Rate</key><integer>44100</integer>
			<key>Skip Count</key><integer>1</integer>
			<key>Skip Date</key><date>2017-03-08T02:04:35Z</date>
			<key>Rating</key><integer>100</integer>
			<key>Album Rating</key><integer>100</integer>
			<key>Album Rating Computed</key><true/>
			<key>Sort Artist</key><string>Swallows</string>
			<key>Persistent ID</key><string>F95EC6B8C9A60240</string>
			<key>Track Type</key><string>File</string>
			<key>Location</key><string>file:///Volumes/LAVALAMP/music/iTunes/YouTube/Naughty/The%20Swallows%20-%20It%20Ain't%20the%20Meat%20(1951).mp3</string>
			<key>File Folder Count</key><integer>4</integer>
			<key>Library Folder Count</key><integer>1</integer>
		</dict>
		<key>15193</key>
		<dict>
			<key>Track ID</key><integer>15193</integer>
			<key>Name</key><string>Sixty Minute Man</string>
			<key>Artist</key><string>Billy Ward and The Dominoes</string>
			<key>Album</key><string>YouTube</string>
			<key>Kind</key><string>MPEG audio file</string>
			<key>Size</key><integer>3618107</integer>
			<key>Total Time</key><integer>150151</integer>
			<key>Date Modified</key><date>2017-03-07T07:47:55Z</date>
			<key>Date Added</key><date>2017-03-07T07:47:43Z</date>
			<key>Bit Rate</key><integer>192</integer>
			<key>Sample Rate</key><integer>44100</integer>
			<key>Rating</key><integer>100</integer>
			<key>Album Rating</key><integer>100</integer>
			<key>Album Rating Computed</key><true/>
			<key>Persistent ID</key><string>51BB57260CC28F69</string>
			<key>Track Type</key><string>File</string>
			<key>Location</key><string>file:///Volumes/LAVALAMP/music/iTunes/YouTube/Naughty/Billy%20Ward%20and%20The%20Dominoes%20-%20Sixty%20Minute%20Man.mp3</string>
			<key>File Folder Count</key><integer>4</integer>
			<key>Library Folder Count</key><integer>1</integer>
		</dict>
		<key>15195</key>
		<dict>
			<key>Track ID</key><integer>15195</integer>
			<key>Name</key><string>Big Fat Mamas Are Back in Style</string>
			<key>Artist</key><string>Bull Moose Jackson</string>
			<key>Album</key><string>YouTube</string>
			<key>Kind</key><string>MPEG audio file</string>
			<key>Size</key><integer>3390946</integer>
			<key>Total Time</key><integer>141113</integer>
			<key>Date Modified</key><date>2017-03-07T07:52:03Z</date>
			<key>Date Added</key><date>2017-03-07T07:51:44Z</date>
			<key>Bit Rate</key><integer>192</integer>
			<key>Sample Rate</key><integer>44100</integer>
			<key>Rating</key><integer>100</integer>
			<key>Album Rating</key><integer>100</integer>
			<key>Album Rating Computed</key><true/>
			<key>Persistent ID</key><string>96FC18C4D1B9432F</string>
			<key>Track Type</key><string>File</string>
			<key>Location</key><string>file:///Volumes/LAVALAMP/music/iTunes/Bull%20Moose%20Jackson/YouTube/Bull%20Moose%20Jackson%20-%20Big%20Fat%20Mamas%20Are%20Back%20in%20Style.mp3</string>
			<key>File Folder Count</key><integer>4</integer>
			<key>Library Folder Count</key><integer>1</integer>
		</dict>
		<key>15197</key>
		<dict>
			<key>Track ID</key><integer>15197</integer>
			<key>Name</key><string>Big Ten Inch</string>
			<key>Artist</key><string>Bull Moose Jackson</string>
			<key>Album</key><string>YouTube</string>
			<key>Kind</key><string>MPEG audio file</string>
			<key>Size</key><integer>3251577</integer>
			<key>Total Time</key><integer>134922</integer>
			<key>Date Modified</key><date>2017-03-07T07:41:36Z</date>
			<key>Date Added</key><date>2017-03-07T07:51:44Z</date>
			<key>Bit Rate</key><integer>192</integer>
			<key>Sample Rate</key><integer>44100</integer>
			<key>Rating</key><integer>100</integer>
			<key>Album Rating</key><integer>100</integer>
			<key>Album Rating Computed</key><true/>
			<key>Sort Album</key><string>YouTube</string>
			<key>Persistent ID</key><string>3E7B50AB5C4F7AA9</string>
			<key>Track Type</key><string>File</string>
			<key>Location</key><string>file:///Volumes/LAVALAMP/music/iTunes/Bull%20Moose%20Jackson/YouTube/Bull%20Moose%20Jackson%20-%20Big%20Ten%20Inch.mp3</string>
			<key>File Folder Count</key><integer>4</integer>
			<key>Library Folder Count</key><integer>1</integer>
		</dict>
		<key>15199</key>
		<dict>
			<key>Track ID</key><integer>15199</integer>
			<key>Name</key><string>I Want a Bowlegged Woman (1947)</string>
			<key>Artist</key><string>Bull Moose Jackson</string>
			<key>Album</key><string>YouTube</string>
			<key>Kind</key><string>MPEG audio file</string>
			<key>Size</key><integer>4358939</integer>
			<key>Total Time</key><integer>181446</integer>
			<key>Year</key><integer>1947</integer>
			<key>Date Modified</key><date>2017-03-07T07:39:47Z</date>
			<key>Date Added</key><date>2017-03-07T07:51:44Z</date>
			<key>Bit Rate</key><integer>192</integer>
			<key>Sample Rate</key><integer>44100</integer>
			<key>Rating</key><integer>100</integer>
			<key>Album Rating</key><integer>100</integer>
			<key>Album Rating Computed</key><true/>
			<key>Sort Album</key><string>YouTube</string>
			<key>Persistent ID</key><string>5F0B86E4D7E131A0</string>
			<key>Track Type</key><string>File</string>
			<key>Location</key><string>file:///Volumes/LAVALAMP/music/iTunes/Bull%20Moose%20Jackson/YouTube/Bull%20Moose%20Jackson%20-%20I%20Want%20a%20Bowlegged%20Woman%20(1947).mp3</string>
			<key>File Folder Count</key><integer>4</integer>
			<key>Library Folder Count</key><integer>1</integer>
		</dict>
		<key>15207</key>
		<dict>
			<key>Track ID</key><integer>15207</integer>
			<key>Name</key><string>Sittin' On It All The Time (1948)</string>
			<key>Artist</key><string>Wynonie Harris</string>
			<key>Album</key><string>YouTube</string>
			<key>Kind</key><string>MPEG audio file</string>
			<key>Size</key><integer>3861150</integer>
			<key>Total Time</key><integer>160705</integer>
			<key>Year</key><integer>1948</integer>
			<key>Date Modified</key><date>2017-03-07T08:05:38Z</date>
			<key>Date Added</key><date>2017-03-07T08:05:14Z</date>
			<key>Bit Rate</key><integer>192</integer>
			<key>Sample Rate</key><integer>44100</integer>
			<key>Rating</key><integer>100</integer>
			<key>Album Rating</key><integer>100</integer>
			<key>Album Rating Computed</key><true/>
			<key>Persistent ID</key><string>008BD2DBFD3E3282</string>
			<key>Track Type</key><string>File</string>
			<key>Location</key><string>file:///Volumes/LAVALAMP/music/iTunes/Wynonie%20Harris/YouTube/Wynonie%20Harris%20-%20Sittin'%20On%20It%20All%20The%20Time%20(1948).mp3</string>
			<key>File Folder Count</key><integer>4</integer>
			<key>Library Folder Count</key><integer>1</integer>
		</dict>
		<key>15209</key>
		<dict>
			<key>Track ID</key><integer>15209</integer>
			<key>Name</key><string>All She Wants To Do Is Rock</string>
			<key>Artist</key><string>Wynonie Harris</string>
			<key>Album</key><string>YouTube</string>
			<key>Kind</key><string>MPEG audio file</string>
			<key>Size</key><integer>3652379</integer>
			<key>Total Time</key><integer>152006</integer>
			<key>Date Modified</key><date>2017-03-07T08:07:13Z</date>
			<key>Date Added</key><date>2017-03-07T08:07:00Z</date>
			<key>Bit Rate</key><integer>192</integer>
			<key>Sample Rate</key><integer>44100</integer>
			<key>Play Count</key><integer>1</integer>
			<key>Play Date</key><integer>3571752979</integer>
			<key>Play Date UTC</key><date>2017-03-08T01:36:19Z</date>
			<key>Skip Count</key><integer>1</integer>
			<key>Skip Date</key><date>2017-03-08T02:06:21Z</date>
			<key>Rating</key><integer>100</integer>
			<key>Album Rating</key><integer>100</integer>
			<key>Album Rating Computed</key><true/>
			<key>Persistent ID</key><string>E35C25DC74D6170F</string>
			<key>Track Type</key><string>File</string>
			<key>Location</key><string>file:///Volumes/LAVALAMP/music/iTunes/Wynonie%20Harris/YouTube/Wynonie%20Harris%20-%20All%20She%20Wants%20To%20Do%20Is%20Rock.mp3</string>
			<key>File Folder Count</key><integer>4</integer>
			<key>Library Folder Count</key><integer>1</integer>
		</dict>
		<key>15211</key>
		<dict>
			<key>Track ID</key><integer>15211</integer>
			<key>Name</key><string>Keep On Churnin' ('Til The Butter Come)</string>
			<key>Artist</key><string>Wynonie Harris</string>
			<key>Album</key><string>YouTube</string>
			<key>Kind</key><string>MPEG audio file</string>
			<key>Size</key><integer>4235412</integer>
			<key>Total Time</key><integer>175830</integer>
			<key>Date Modified</key><date>2017-03-07T08:09:17Z</date>
			<key>Date Added</key><date>2017-03-07T08:09:01Z</date>
			<key>Bit Rate</key><integer>192</integer>
			<key>Sample Rate</key><integer>44100</integer>
			<key>Play Count</key><integer>1</integer>
			<key>Play Date</key><integer>3571750603</integer>
			<key>Play Date UTC</key><date>2017-03-08T00:56:43Z</date>
			<key>Rating</key><integer>100</integer>
			<key>Album Rating</key><integer>100</integer>
			<key>Album Rating Computed</key><true/>
			<key>Persistent ID</key><string>F369248A7759667A</string>
			<key>Track Type</key><string>File</string>
			<key>Location</key><string>file:///Volumes/LAVALAMP/music/iTunes/Wynonie%20Harris/YouTube/Wynonie%20Harris%20-%20Keep%20On%20Churnin'%20('Til%20The%20Butter%20Come).mp3</string>
			<key>File Folder Count</key><integer>4</integer>
			<key>Library Folder Count</key><integer>1</integer>
		</dict>
		<key>15213</key>
		<dict>
			<key>Track ID</key><integer>15213</integer>
			<key>Name</key><string>Lollipop Mama</string>
			<key>Artist</key><string>Wynonie Harris</string>
			<key>Album</key><string>YouTube</string>
			<key>Kind</key><string>MPEG audio file</string>
			<key>Size</key><integer>4098133</integer>
			<key>Total Time</key><integer>170579</integer>
			<key>Date Modified</key><date>2017-03-07T08:17:05Z</date>
			<key>Date Added</key><date>2017-03-07T08:16:46Z</date>
			<key>Bit Rate</key><integer>192</integer>
			<key>Sample Rate</key><integer>44100</integer>
			<key>Play Count</key><integer>1</integer>
			<key>Play Date</key><integer>3571751113</integer>
			<key>Play Date UTC</key><date>2017-03-08T01:05:13Z</date>
			<key>Rating</key><integer>100</integer>
			<key>Album Rating</key><integer>100</integer>
			<key>Album Rating Computed</key><true/>
			<key>Persistent ID</key><string>CDC98E7D9CA287A9</string>
			<key>Track Type</key><string>File</string>
			<key>Location</key><string>file:///Volumes/LAVALAMP/music/iTunes/Wynonie%20Harris/YouTube/Wynonie%20Harris%20-%20Lollipop%20Mama.mp3</string>
			<key>File Folder Count</key><integer>4</integer>
			<key>Library Folder Count</key><integer>1</integer>
		</dict>
		<key>15233</key>
		<dict>
			<key>Track ID</key><integer>15233</integer>
			<key>Name</key><string>Lovin' Machine (1951)</string>
			<key>Artist</key><string>Wynonie Harris</string>
			<key>Album</key><string>YouTube</string>
			<key>Kind</key><string>MPEG audio file</string>
			<key>Size</key><integer>3857200</integer>
			<key>Total Time</key><integer>160156</integer>
			<key>Year</key><integer>1951</integer>
			<key>Date Modified</key><date>2017-03-08T07:02:34Z</date>
			<key>Date Added</key><date>2017-03-08T07:01:25Z</date>
			<key>Bit Rate</key><integer>192</integer>
			<key>Sample Rate</key><integer>44100</integer>
			<key>Play Count</key><integer>3</integer>
			<key>Play Date</key><integer>3571934225</integer>
			<key>Play Date UTC</key><date>2017-03-10T03:57:05Z</date>
			<key>Rating</key><integer>100</integer>
			<key>Album Rating</key><integer>100</integer>
			<key>Album Rating Computed</key><true/>
			<key>Sort Album</key><string>YouTube</string>
			<key>Persistent ID</key><string>9F04096FB6214466</string>
			<key>Track Type</key><string>File</string>
			<key>Location</key><string>file:///Volumes/LAVALAMP/music/iTunes/Wynonie%20Harris/YouTube/Wynonie%20Harris%20-%20Lovin'%20Machine%20(1951).mp3</string>
			<key>File Folder Count</key><integer>4</integer>
			<key>Library Folder Count</key><integer>1</integer>
		</dict>
		<key>15241</key>
		<dict>
			<key>Track ID</key><integer>15241</integer>
			<key>Name</key><string>Nosey Joe</string>
			<key>Artist</key><string>Bull Moose Jackson</string>
			<key>Album</key><string>YouTube</string>
			<key>Kind</key><string>MPEG audio file</string>
			<key>Size</key><integer>3774005</integer>
			<key>Total Time</key><integer>157074</integer>
			<key>Date Modified</key><date>2017-03-08T07:13:31Z</date>
			<key>Date Added</key><date>2017-03-08T07:13:13Z</date>
			<key>Bit Rate</key><integer>192</integer>
			<key>Sample Rate</key><integer>44100</integer>
			<key>Play Count</key><integer>1</integer>
			<key>Play Date</key><integer>3571806951</integer>
			<key>Play Date UTC</key><date>2017-03-08T16:35:51Z</date>
			<key>Rating</key><integer>100</integer>
			<key>Album Rating</key><integer>100</integer>
			<key>Album Rating Computed</key><true/>
			<key>Persistent ID</key><string>8F25DA446D54B249</string>
			<key>Track Type</key><string>File</string>
			<key>Location</key><string>file:///Volumes/LAVALAMP/music/iTunes/Bull%20Moose%20Jackson/YouTube/Bull%20Moose%20Jackson%20-%20Nosey%20Joe.mp3</string>
			<key>File Folder Count</key><integer>4</integer>
			<key>Library Folder Count</key><integer>1</integer>
		</dict>
	</dict>
	<key>Playlists</key>
	<array>
		<dict>
			<key>Name</key><string>Naughty!</string>
			<key>Description</key><string></string>
			<key>Playlist ID</key><integer>34201</integer>
			<key>Playlist Persistent ID</key><string>5D44A5B63B650EDB</string>
			<key>All Items</key><true/>
			<key>Playlist Items</key>
			<array>
				<dict>
					<key>Track ID</key><integer>12367</integer>
				</dict>
				<dict>
					<key>Track ID</key><integer>15191</integer>
				</dict>
				<dict>
					<key>Track ID</key><integer>15173</integer>
				</dict>
				<dict>
					<key>Track ID</key><integer>15195</integer>
				</dict>
				<dict>
					<key>Track ID</key><integer>15197</integer>
				</dict>
				<dict>
					<key>Track ID</key><integer>15199</integer>
				</dict>
				<dict>
					<key>Track ID</key><integer>15193</integer>
				</dict>
				<dict>
					<key>Track ID</key><integer>15189</integer>
				</dict>
				<dict>
					<key>Track ID</key><integer>15185</integer>
				</dict>
				<dict>
					<key>Track ID</key><integer>15187</integer>
				</dict>
				<dict>
					<key>Track ID</key><integer>14171</integer>
				</dict>
				<dict>
					<key>Track ID</key><integer>15165</integer>
				</dict>
				<dict>
					<key>Track ID</key><integer>15171</integer>
				</dict>
				<dict>
					<key>Track ID</key><integer>15167</integer>
				</dict>
				<dict>
					<key>Track ID</key><integer>15163</integer>
				</dict>
				<dict>
					<key>Track ID</key><integer>13087</integer>
				</dict>
				<dict>
					<key>Track ID</key><integer>14135</integer>
				</dict>
				<dict>
					<key>Track ID</key><integer>15161</integer>
				</dict>
				<dict>
					<key>Track ID</key><integer>13939</integer>
				</dict>
				<dict>
					<key>Track ID</key><integer>15157</integer>
				</dict>
				<dict>
					<key>Track ID</key><integer>15159</integer>
				</dict>
				<dict>
					<key>Track ID</key><integer>13069</integer>
				</dict>
				<dict>
					<key>Track ID</key><integer>14921</integer>
				</dict>
				<dict>
					<key>Track ID</key><integer>12311</integer>
				</dict>
				<dict>
					<key>Track ID</key><integer>15043</integer>
				</dict>
				<dict>
					<key>Track ID</key><integer>12803</integer>
				</dict>
				<dict>
					<key>Track ID</key><integer>14759</integer>
				</dict>
				<dict>
					<key>Track ID</key><integer>14753</integer>
				</dict>
				<dict>
					<key>Track ID</key><integer>14773</integer>
				</dict>
				<dict>
					<key>Track ID</key><integer>13997</integer>
				</dict>
				<dict>
					<key>Track ID</key><integer>14763</integer>
				</dict>
				<dict>
					<key>Track ID</key><integer>12349</integer>
				</dict>
				<dict>
					<key>Track ID</key><integer>13085</integer>
				</dict>
				<dict>
					<key>Track ID</key><integer>15137</integer>
				</dict>
				<dict>
					<key>Track ID</key><integer>15179</integer>
				</dict>
				<dict>
					<key>Track ID</key><integer>15181</integer>
				</dict>
				<dict>
					<key>Track ID</key><integer>15207</integer>
				</dict>
				<dict>
					<key>Track ID</key><integer>15209</integer>
				</dict>
				<dict>
					<key>Track ID</key><integer>15211</integer>
				</dict>
				<dict>
					<key>Track ID</key><integer>15213</integer>
				</dict>
				<dict>
					<key>Track ID</key><integer>14927</integer>
				</dict>
				<dict>
					<key>Track ID</key><integer>14973</integer>
				</dict>
				<dict>
					<key>Track ID</key><integer>15233</integer>
				</dict>
				<dict>
					<key>Track ID</key><integer>15241</integer>
				</dict>
				<dict>
					<key>Track ID</key><integer>15233</integer>
				</dict>
				<dict>
					<key>Track ID</key><integer>13113</integer>
				</dict>
				<dict>
					<key>Track ID</key><integer>13279</integer>
				</dict>
			</array>
		</dict>
	</array>
</dict>
</plist>
